src/fitrepo/__init__.py
src/fitrepo/fitrepo.py
fitrepo-0.1.432.dist-info/METADATA
fitrepo-0.1.432.dist-info/WHEEL
fitrepo-0.1.432.dist-info/entry_points.txt
fitrepo-0.1.432.dist-info/licenses/LICENSE.md
fitrepo-0.1.432.dist-info/RECORD
