Metadata-Version: 2.4
Name: fitrepo
Version: 0.1.432
Summary: Tool for managing Git repositories in a Fossil monorepo
Project-URL: Homepage, https://github.com/bitnom/fitrepo
Project-URL: Bug Tracker, https://github.com/bitnom/fitrepo/issues
Author-email: bitnom <14287229+bitnom@users.noreply.github.com>
License: Apache-2.0
License-File: LICENSE.md
Requires-Python: <3.14,>=3.9
Requires-Dist: git-filter-repo>=2.47.0
Provides-Extra: dev
Requires-Dist: black; extra == 'dev'
Requires-Dist: isort; extra == 'dev'
Requires-Dist: pytest-cov; extra == 'dev'
Requires-Dist: pytest>=7.0.0; extra == 'dev'
